pydaasiot/__init__.py
pydaasiot/_core.cpython-313-x86_64-linux-gnu.so
pydaasiot-0.2.1.dist-info/METADATA
pydaasiot-0.2.1.dist-info/WHEEL
pydaasiot-0.2.1.dist-info/RECORD
pydaasiot-0.2.1.dist-info/licenses/LICENSE
