Metadata-Version: 2.2
Name: pydaasiot
Version: 0.2.1
Summary: Python bindings for DaaS-IoT (Windows + Linux manylinux).
Author-Email: Tuo Nome <you@example.com>
Classifier: Programming Language :: Python :: 3
Classifier: Programming Language :: Python :: Implementation :: CPython
Classifier: Programming Language :: C++
Classifier: Operating System :: Microsoft :: Windows
Classifier: Operating System :: POSIX :: Linux
Classifier: License :: OSI Approved :: MIT License
Project-URL: Homepage, https://github.com/tuo-org/pydaasiot
Project-URL: Issues, https://github.com/tuo-org/pydaasiot/issues
Requires-Python: >=3.9
